iceberg_tools/__init__.py
iceberg_tools/util.py
iceberg_tools/cli/__init__.py
iceberg_tools/cli/data.py
iceberg_tools/cli/schema.py
iceberg_tools/data/__init__.py
iceberg_tools/data/pfb.py
iceberg_tools/data/report.py
iceberg_tools/data/migrator/__init__.py
iceberg_tools/data/simplifier/__init__.py
iceberg_tools/data/simplifier/oid_lookup.py
iceberg_tools/graph/__init__.py
iceberg_tools/schema/__init__.py
iceberg_tools/schema/bmeg.py
iceberg_tools/schema/gen3.py
iceberg_tools/schema/gen3_validator.py
iceberg_tools/schema/graph.py
iceberg_tools/schema/simplified.py
iceberg_tools/schema/simplified_validator.py
iceberg_tools/schema/fhir_resources/__init__.py
iceberg_tools/schema/fhir_resources/binding_lookup.py
tests/integration/__init__.py
tests/integration/__pycache__/__init__.cpython-39.pyc
tests/integration/bmeg/__init__.py
tests/integration/bmeg/conftest.py
tests/integration/bmeg/test_edge_load_granular_reference.py
tests/integration/bmeg/test_edge_validator.py
tests/integration/bmeg/test_invalid_edges.py
tests/integration/bmeg/test_lathe_lint.py
tests/integration/bmeg/test_negative_trivial_vertex_load.py
tests/integration/bmeg/test_schema.py
tests/integration/bmeg/test_schema_load.py
tests/integration/bmeg/test_spot_check_embedded_type.py
tests/integration/bmeg/test_trivial_edge_load.py
tests/integration/bmeg/test_trivial_vertex_load.py
tests/integration/bmeg/test_yaml_anonymous_schemas.py
tests/integration/data/__init__.py
tests/integration/data/config.yaml
tests/integration/data/conftest.py
tests/integration/data/test_pfb.py
tests/integration/data/simplifier/__init__.py
tests/integration/data/simplifier/test_simplify.py
tests/integration/gen3/__init__.py
tests/integration/gen3/conftest.py
tests/integration/gen3/test_codeable_concept.py
tests/integration/gen3/test_embedded_types.py
tests/integration/gen3/test_identifiers.py
tests/integration/gen3/test_individual_yaml.py
tests/integration/gen3/test_keys.py
tests/integration/gen3/test_primitive.py
iceberg_tools-0.0.5.dist-info/METADATA
iceberg_tools-0.0.5.dist-info/WHEEL
iceberg_tools-0.0.5.dist-info/entry_points.txt
iceberg_tools-0.0.5.dist-info/top_level.txt
iceberg_tools-0.0.5.dist-info/RECORD
